encrypted_datasets/__init__.py
encrypted_datasets/src/serializer.py
encrypted_datasets-1.0.12.dist-info/METADATA
encrypted_datasets-1.0.12.dist-info/WHEEL
encrypted_datasets-1.0.12.dist-info/RECORD
