Metadata-Version: 2.1
Name: encrypted-datasets
Version: 1.0.12
Summary: Convenience functions for symetrically encrypting/decrypting huggingface Datasets
Author: nvjoshi2
Author-email: nvj1300@gmail.com
Requires-Python: >=3.9,<4.0
Classifier: Programming Language :: Python :: 3
Classifier: Programming Language :: Python :: 3.9
Classifier: Programming Language :: Python :: 3.10
Classifier: Programming Language :: Python :: 3.11
Classifier: Programming Language :: Python :: 3.12
Requires-Dist: boto3 (>=1.35.29,<2.0.0)
Requires-Dist: cryptography (>=43.0.1,<44.0.0)
Requires-Dist: datasets (>=3.0.1,<4.0.0)
Requires-Dist: huggingface-hub (>=0.29.3,<0.30.0)
Requires-Dist: pandas (>=2.2.3,<3.0.0)
